incendiary/__init__.py
incendiary/loggers.py
incendiary/xray/__init__.py
incendiary/xray/app.py
incendiary/xray/config.py
incendiary/xray/contexts.py
incendiary/xray/factories.py
incendiary/xray/hooks.py
incendiary/xray/middlewares.py
incendiary/xray/mixins.py
incendiary/xray/sampling.py
incendiary/xray/services.py
incendiary/xray/utils.py
insanic_incendiary-0.2.0.dist-info/LICENSE
insanic_incendiary-0.2.0.dist-info/METADATA
insanic_incendiary-0.2.0.dist-info/WHEEL
insanic_incendiary-0.2.0.dist-info/top_level.txt
insanic_incendiary-0.2.0.dist-info/RECORD
