Metadata-Version: 2.1
Name: insanic-incendiary
Version: 0.2.0
Summary: tracing for insanic
Home-page: https://github.com/crazytruth/incendiary
Author: Kwang Jin Kim
Author-email: kwangjinkim@gmail.com
License: MIT
Keywords: opentracing zipkin msa microservice xray tracing
Platform: UNKNOWN
Classifier: Development Status :: 3 - Alpha
Classifier: License :: OSI Approved :: MIT License
Classifier: Programming Language :: Python :: 3.6
Classifier: Programming Language :: Python :: 3.7
Classifier: Programming Language :: Python :: 3.8
Classifier: Intended Audience :: Developers
Requires-Dist: insanic-framework (<=0.10.0,>=0.9.0)
Requires-Dist: aws-xray-sdk
